{
  "pages": [
    {
      "index": 0,
      "markdown": "Permabond\n\nEngineering Adhesives\n\nPERMABOND® ET538\n\nTwo-Part Epoxy\n\nTechnical Datasheet\n\n# Features &amp; Benefits\n\n- Adhesion to a wide variety of substrates\n- Full cure at room temperature\n- Easy to apply\n- High shear and peel strength\n- Good impact strength\n- Good chemical resistance\n- Non-drip rheology\n\n# Description\n\nPERMABOND® ET538 is a structural, room temperature curing epoxy adhesive that has excellent adhesion to a wide variety of surfaces such as wood, metal, ceramics and many plastic and composite materials. It exhibits good resistance to petrol, oils and water and has an extended cure time making it suitable for larger applications and batch production processes. Its thixotropic \"non-slump\" nature makes it suitable for gap filling or vertical application.\n\n## Physical Properties of Uncured Adhesive\n\n|   | ET538 A side | ET538 B side  |\n| --- | --- | --- |\n|  Chemical composition | Epoxy Resin | Polyamine Hardener  |\n|  Appearance | White | Dark grey  |\n|  Viscosity @ 25°C | 20rpm: 75,000 mPa.s (cP)\n2.5rpm: 225,000 mPa.s (cP) | 20rpm: 30,000 mPa.s (cP)\n2rpm: 60,000 mPa.s (cP)  |\n|  Specific gravity | 1.1 | 1.4  |\n\n## Typical Curing Properties\n\n|  Mix ratio | 1:1 by volume\n100:130 by weight  |\n| --- | --- |\n|  Maximum gap fill | 5 mm 0.2 in  |\n|  Usable / pot life @23°C | 120-150 mins  |\n|  Handling time @23°C | 3-5 hours  |\n|  Working strength @23°C | 24 hours  |\n|  Full cure @23°C | 72 hours  |\n\n## Typical Performance of Cured Adhesive\n\n|  Shear strength* (ISO4587) | Mild steel: 25-30 N/mm² (3625-4350psi)\nAluminium: 22-26 N/mm² (3190-3770psi)\nStainless Steel: 28-32 N/mm² (4060-4640psi)\nZinc: 17-20 N/mm² (2500 - 2900 psi)\nCarbon Fibre: 20-24 N/mm² (2900-3480psi)\nFRP Glass/Polyester: 6-8 N/mm² (870-1160psi)\nFRP Glass/Epoxy: 18-22 N/mm² (2610-3190psi)\nPolycarbonate: 3-5 N/mm² (435-725psi)\nPA6 30% filled: 3-5 N/mm² (435-725psi)  |\n| --- | --- |\n|  Peel strength (aluminium) (ISO4578) | 60-80 N/25mm (13-18 PIW)  |\n|  Hardness (ISO868) | 70-80 Shore D  |\n|  Elongation at break (ISO37) | 4-8%  |\n|  Glass transition temperature Tg | 45-55°C (113-131°F)  |\n|  Dielectric strength | 15-25 kV/ mm  |\n|  Thermal conductivity | 0.55 W/(m.K)  |\n\n*Strength results will vary depending on the level of surface preparation and gap.\n\n## Strength Development\n\n![img-0.jpeg](img-0.jpeg)\n\nGraph shows typical strength development of bonded components. An increase of 8°C in temperature will halve the cure time. Lower temperatures will result in a slower cure time.\n\nThe information given and the recommendations made herein are based on our research and are believed to be accurate but no guarantee of their accuracy is made. In every case we urge and recommend that purchasers before using any product in full-scale production make their own tests to determine to their own satisfaction whether the product is of acceptable quality and is suitable for their particular purpose under their own operating conditions. THE PRODUCTS DISCLOSED HEREIN ARE SOLD WITHOUT ANY WARRANTY AS TO MERCHANTABILITY OR FITNESS FOR A PARTICULAR PURPOSE OR ANY OTHER WARRANTY, EXPRESS OR IMPLIED.\n\nNo representative of ours has any authority to waive or change the foregoing provisions but, subject to such provisions, our engineers are available to assist purchasers in adapting our products to their needs and to the circumstances prevailing in their business. Nothing contained herein shall be construed to imply the non-existence of any relevant patents or to constitute a permission, inducement or recommendation to practice any invention covered by any patent, without authority from the owner of this patent. We also expect purchasers to use our products in accordance with the guiding principles of the Chemical Manufacturers Association's Responsible Care® program.\n\nPermabond ET538\n\nGlobal TDS Revision 8\n\n12 May 2022\n\nFOR PROFESSIONAL OR INDUSTRIAL USE ONLY. KEEP OUT OF REACH OF CHILDREN",
      "images": [
        {
          "id": "img-0.jpeg",
          "top_left_x": 396,
          "top_left_y": 636,
          "bottom_right_x": 658,
          "bottom_right_y": 828,
          "image_base64": null,
          "image_annotation": null
        }
      ],
      "dimensions": {
        "dpi": 87,
        "height": 1018,
        "width": 720
      },
      "tables": [],
      "hyperlinks": [],
      "header": null,
      "footer": null
    },
    {
      "index": 1,
      "markdown": "Hot Strength\n![img-1.jpeg](img-1.jpeg)\nHot strength* shear strength tests performed on mild steel. Fully cured specimens conditioned to pull temperature for 30 minutes before testing at temperature.\n\nET538 can withstand higher temperatures for brief periods (such as for paint baking and wave soldering processes) providing the joint is not unduly stressed. The minimum temperature the cured adhesive can be exposed to is $-40^{\\circ}\\mathrm{C}$ ($-40^{\\circ}\\mathrm{F}$) depending on the materials being bonded.\n\n## Additional Information\n\nThis product is not recommended for use in contact with strong oxidizing materials.\n\nInformation regarding the safe handling of this material may be obtained from the safety data sheet.\n\nUsers are reminded that all materials, whether innocuous or not, should be handled in accordance with the principles of good industrial hygiene.\n\n## Surface Preparation\n\nSurfaces should be clean, dry and grease-free before applying the adhesive. Use a suitable solvent (such as acetone or isopropanol) for the degreasing of surfaces. Some metals such as aluminium, copper and its alloys will benefit from light abrasion with emery cloth (or similar), to remove the oxide layer.\n\n## Directions for Use\n\n1. Dual cartridges:\na) Insert the cartridge into the application gun and guide the plunger into the cartridge.\nb) Remove the cartridge cap and dispense material until both sides are flowing.\nc) Attach the static mixer to the end of the cartridge and begin dispensing the material.\n2. Apply material to one of the substrates.\n3. Join the parts. Parts must be joined within the usable pot life of mixing the two epoxy components.\n4. Large quantities and/or higher temperature will decrease the usable life or pot life.\n5. Apply pressure to the assembly by clamping until handling strength is obtained.\n6. Full cure will be obtained after 72 hours at $23^{\\circ}\\mathrm{C}$ (73°F). Heat can be used to accelerate the curing process.\n\n## Storage &amp; Handling\n\n|  Storage Temperature | 5 to 25°C (41 to 77°F)  |\n| --- | --- |\n\n## Video Links\n\nSurface preparation:\nhttps://youtu.be/8CMOMP7hXjU\n\n![img-2.jpeg](img-2.jpeg)\n\nTwo-part epoxy directions for use:\nhttps://youtu.be/GRX1RyknYqc\n\n![img-3.jpeg](img-3.jpeg)\n\nwww.permabond.com\n\n- UK: 0800 975 9800\n- General Enquiries: +44 (0)1962 711661\n- US: 732-868-1372\n- Asia: +86 21 5773 4913\n\ninfo.europe@permabond.com\n\ninfo.americas@permabond.com\n\ninfo.asia@permabond.com\n\nThe information given and the recommendations made herein are based on our research and are believed to be accurate but no guarantee of their accuracy is made. In every case we urge and recommend that purchasers before using any product in full-scale production make their own tests to determine to their own satisfaction whether the product is of acceptable quality and is suitable for their particular purpose under their own operating conditions. THE PRODUCTS DISCLOSED HEREIN ARE SOLD WITHOUT ANY WARRANTY AS TO MERCHANTABILITY OR FITNESS FOR A PARTICULAR PURPOSE OR ANY OTHER WARRANTY, EXPRESS OR IMPLIED.\n\nNo representative of ours has any authority to waive or change the foregoing provisions but, subject to such provisions, our engineers are available to assist purchasers in adapting our products to their needs and to the circumstances prevailing in their business. Nothing contained herein shall be construed to imply the non-existence of any relevant patents or to constitute a permission, inducement or recommendation to practice any invention covered by any patent, without authority from the owner of this patent. We also expect purchasers to use our products in accordance with the guiding principles of the Chemical Manufacturers Association's Responsible Care® program.\n\nPermabond ET538\n\nGlobal TDS Revision 8\n\n12 May 2022\n\nFOR PROFESSIONAL OR INDUSTRIAL USE ONLY. KEEP OUT OF REACH OF CHILDREN",
      "images": [
        {
          "id": "img-1.jpeg",
          "top_left_x": 65,
          "top_left_y": 110,
          "bottom_right_x": 328,
          "bottom_right_y": 284,
          "image_base64": null,
          "image_annotation": null
        },
        {
          "id": "img-2.jpeg",
          "top_left_x": 599,
          "top_left_y": 489,
          "bottom_right_x": 651,
          "bottom_right_y": 542,
          "image_base64": null,
          "image_annotation": null
        },
        {
          "id": "img-3.jpeg",
          "top_left_x": 599,
          "top_left_y": 555,
          "bottom_right_x": 651,
          "bottom_right_y": 608,
          "image_base64": null,
          "image_annotation": null
        }
      ],
      "dimensions": {
        "dpi": 87,
        "height": 1018,
        "width": 720
      },
      "tables": [],
      "hyperlinks": [
        "https://youtu.be/8CMOMP7hXjU",
        "https://youtu.be/GRX1RyknYqc"
      ],
      "header": null,
      "footer": null
    }
  ],
  "model": "mistral-ocr-latest",
  "usage_info": {
    "pages_processed": 2,
    "doc_size_bytes": 326570
  },
  "document_annotation": null
}
